JavaShejimoshiZuijiaShijianChuyiFix1/README.md
JavaShejimoshiZuijiaShijianChuyiFix1/__init__.py
JavaShejimoshiZuijiaShijianChuyiFix1/__main__.py
JavaShejimoshiZuijiaShijianChuyiFix1/file.epub
JavaShejimoshiZuijiaShijianChuyiFix1/index.html
JavaShejimoshiZuijiaShijianChuyiFix1/css/__init__.py
JavaShejimoshiZuijiaShijianChuyiFix1/css/annotations.css
JavaShejimoshiZuijiaShijianChuyiFix1/css/main.css
JavaShejimoshiZuijiaShijianChuyiFix1/css/normalize.css
JavaShejimoshiZuijiaShijianChuyiFix1/css/popup.css
JavaShejimoshiZuijiaShijianChuyiFix1/font/__init__.py
JavaShejimoshiZuijiaShijianChuyiFix1/font/fontello.eot
JavaShejimoshiZuijiaShijianChuyiFix1/font/fontello.svg
JavaShejimoshiZuijiaShijianChuyiFix1/font/fontello.ttf
JavaShejimoshiZuijiaShijianChuyiFix1/font/fontello.woff
JavaShejimoshiZuijiaShijianChuyiFix1/img/__init__.py
JavaShejimoshiZuijiaShijianChuyiFix1/img/annotator-glyph-sprite.png
JavaShejimoshiZuijiaShijianChuyiFix1/img/annotator-icon-sprite.png
JavaShejimoshiZuijiaShijianChuyiFix1/img/apple-touch-icon.png
JavaShejimoshiZuijiaShijianChuyiFix1/img/cancelfullscreen.png
JavaShejimoshiZuijiaShijianChuyiFix1/img/close.png
JavaShejimoshiZuijiaShijianChuyiFix1/img/fullscreen.png
JavaShejimoshiZuijiaShijianChuyiFix1/img/loader.gif
JavaShejimoshiZuijiaShijianChuyiFix1/img/menu-icon.png
JavaShejimoshiZuijiaShijianChuyiFix1/img/save.png
JavaShejimoshiZuijiaShijianChuyiFix1/img/saved.png
JavaShejimoshiZuijiaShijianChuyiFix1/img/settings-s.png
JavaShejimoshiZuijiaShijianChuyiFix1/img/settings.png
JavaShejimoshiZuijiaShijianChuyiFix1/img/star.png
JavaShejimoshiZuijiaShijianChuyiFix1/js/__init__.py
JavaShejimoshiZuijiaShijianChuyiFix1/js/epub.js
JavaShejimoshiZuijiaShijianChuyiFix1/js/epub.min.js
JavaShejimoshiZuijiaShijianChuyiFix1/js/epub.min.map
JavaShejimoshiZuijiaShijianChuyiFix1/js/hooks.min.js
JavaShejimoshiZuijiaShijianChuyiFix1/js/hooks.min.map
JavaShejimoshiZuijiaShijianChuyiFix1/js/reader.js
JavaShejimoshiZuijiaShijianChuyiFix1/js/reader.js.map
java_shejimoshi_zuijia_shijian_chuyi_fix1-2025.3.25.0.dist-info/METADATA
java_shejimoshi_zuijia_shijian_chuyi_fix1-2025.3.25.0.dist-info/WHEEL
java_shejimoshi_zuijia_shijian_chuyi_fix1-2025.3.25.0.dist-info/entry_points.txt
java_shejimoshi_zuijia_shijian_chuyi_fix1-2025.3.25.0.dist-info/top_level.txt
java_shejimoshi_zuijia_shijian_chuyi_fix1-2025.3.25.0.dist-info/RECORD
